raw_data_outputter_graveltr/__init__.py
raw_data_outputter_graveltr/example.py
raw_data_outputter_graveltr/data/my_data.txt
raw_data_outputter_graveltr-0.0.3.dist-info/licenses/LICENSE
raw_data_outputter_graveltr-0.0.3.dist-info/METADATA
raw_data_outputter_graveltr-0.0.3.dist-info/WHEEL
raw_data_outputter_graveltr-0.0.3.dist-info/top_level.txt
raw_data_outputter_graveltr-0.0.3.dist-info/RECORD
