Metadata-Version: 2.4
Name: raw_data_outputter_graveltr
Version: 0.0.3
License-File: LICENSE
Requires-Dist: numpy
Dynamic: license-file
